meu_pacote/__init__.py
meu_pacote/calculadora.py
meu_pacote/strings.py
meu_pacote_exemplo-0.0.1.dist-info/METADATA
meu_pacote_exemplo-0.0.1.dist-info/WHEEL
meu_pacote_exemplo-0.0.1.dist-info/top_level.txt
meu_pacote_exemplo-0.0.1.dist-info/RECORD
