Metadata-Version: 2.4
Name: meu_pacote_exemplo
Version: 0.0.1
Summary: Um pacote de exemplo com funções úteis
Home-page: https://github.com/tiagoosr/simple-package-template
Author: Tiago
Requires-Python: >=3.8
Dynamic: author
Dynamic: description
Dynamic: description-content-type
Dynamic: home-page
Dynamic: requires-python
Dynamic: summary
